easyllm_kit/__init__.py
easyllm_kit/configs/__init__.py
easyllm_kit/configs/base.py
easyllm_kit/configs/hf_config.py
easyllm_kit/configs/llm_base_config.py
easyllm_kit/metrics/__init__.py
easyllm_kit/metrics/base.py
easyllm_kit/models/__init__.py
easyllm_kit/models/base.py
easyllm_kit/models/claude.py
easyllm_kit/models/cpm.py
easyllm_kit/models/deepseek.py
easyllm_kit/models/flan.py
easyllm_kit/models/gemini.py
easyllm_kit/models/gemma.py
easyllm_kit/models/gemma3.py
easyllm_kit/models/llama.py
easyllm_kit/models/llama_vis.py
easyllm_kit/models/llava.py
easyllm_kit/models/mixtral.py
easyllm_kit/models/openai.py
easyllm_kit/models/perplexity.py
easyllm_kit/models/phi4.py
easyllm_kit/models/qwen_vl.py
easyllm_kit/utils/__init__.py
easyllm_kit/utils/app.py
easyllm_kit/utils/config_utils.py
easyllm_kit/utils/data_utils.py
easyllm_kit/utils/hf_utils.py
easyllm_kit/utils/io_utils.py
easyllm_kit/utils/log_utils.py
easyllm_kit/utils/multiprocess.py
easyllm_kit/utils/multithread.py
easyllm_kit/utils/prompt_utils.py
easyllm_kit-0.0.9.5.dist-info/licenses/LICENSE
easyllm_kit-0.0.9.5.dist-info/METADATA
easyllm_kit-0.0.9.5.dist-info/WHEEL
easyllm_kit-0.0.9.5.dist-info/top_level.txt
easyllm_kit-0.0.9.5.dist-info/RECORD
