Metadata-Version: 2.4
Name: easyllm_kit
Version: 0.0.9.5
Summary: An easy recipes of code for large language model
Home-page: https://github.com/iLampard/llm_recipes
Author: iLampard
License: Apache License 2.0
Classifier: Development Status :: 3 - Alpha
Classifier: Intended Audience :: Developers
Classifier: License :: OSI Approved :: Apache Software License
Classifier: Programming Language :: Python :: 3.8
Classifier: Programming Language :: Python :: 3.9
Classifier: Programming Language :: Python :: 3.10
Requires-Python: >=3.8
License-File: LICENSE
Requires-Dist: torch
Requires-Dist: transformers
Requires-Dist: omegaconf
Requires-Dist: registrable
Requires-Dist: huggingface_hub
Requires-Dist: datasets
Requires-Dist: pyyaml
Requires-Dist: openai
Requires-Dist: numpy
Requires-Dist: colorama
Requires-Dist: json-repair
Dynamic: author
Dynamic: classifier
Dynamic: description
Dynamic: description-content-type
Dynamic: home-page
Dynamic: license
Dynamic: license-file
Dynamic: requires-dist
Dynamic: requires-python
Dynamic: summary
